MyPkgManually/__init__.py
MyPkgManually/hello.py
tests/__init__.py
tests/test_hello.py
MyPkgManually-0.1.2.dist-info/LICENSE
MyPkgManually-0.1.2.dist-info/METADATA
MyPkgManually-0.1.2.dist-info/WHEEL
MyPkgManually-0.1.2.dist-info/top_level.txt
MyPkgManually-0.1.2.dist-info/RECORD
